LICENSE
README.md
mpd_art_box.py
setup.cfg
setup.py
mpd_art_box.egg-info/PKG-INFO
mpd_art_box.egg-info/SOURCES.txt
mpd_art_box.egg-info/dependency_links.txt
mpd_art_box.egg-info/entry_points.txt
mpd_art_box.egg-info/requires.txt
mpd_art_box.egg-info/top_level.txt