Metadata-Version: 2.1
Name: mpd-art-box
Version: 0.0.7
Summary: A window containg the cover art for the currently playing MPD song - nothing more
Home-page: https://github.com/nvllsvm/mpd-art-box
Author: Andrew Rabert
Author-email: ar@nullsum.net
License: UNKNOWN
Platform: UNKNOWN
